kst1/__init__.py
kst1/admin.py
kst1/apps.py
kst1/fields.py
kst1/forms.py
kst1/models.py
kst1/states.py
kst1/tests.py
kst1/views.py
kst1/migrations/__init__.py
parth_indian_states_25/__init__.py
parth_indian_states_25/asgi.py
parth_indian_states_25/settings.py
parth_indian_states_25/urls.py
parth_indian_states_25/wsgi.py
parth_indian_states_25-0.1.dist-info/METADATA
parth_indian_states_25-0.1.dist-info/WHEEL
parth_indian_states_25-0.1.dist-info/top_level.txt
parth_indian_states_25-0.1.dist-info/RECORD
